base_audio/__init__.py
base_audio/audio_helper.py
base_audio/common_plot.py
base_audio/errors.py
base_audio/example.py
base_audio/signal_to_spectrogram.py
base_audio/spectrogram_to_signal.py
base_audio-0.1.1.dist-info/AUTHORS
base_audio-0.1.1.dist-info/LICENSE.md
base_audio-0.1.1.dist-info/METADATA
base_audio-0.1.1.dist-info/WHEEL
base_audio-0.1.1.dist-info/top_level.txt
base_audio-0.1.1.dist-info/RECORD
